outdatedLabs/__init__.py
outdatedLabs/secure_model.py
outdatedlabs-0.1.3.dist-info/METADATA
outdatedlabs-0.1.3.dist-info/WHEEL
outdatedlabs-0.1.3.dist-info/top_level.txt
outdatedlabs-0.1.3.dist-info/RECORD
