Metadata-Version: 2.4
Name: outdatedLabs
Version: 0.1.3
Summary: A secure package for training machine learning models
Home-page: https://github.com/Mouli51ch/OutDated
Author: OutDated Team
Author-email: your.email@example.com
Classifier: Development Status :: 3 - Alpha
Classifier: Intended Audience :: Developers
Classifier: License :: OSI Approved :: MIT License
Classifier: Programming Language :: Python :: 3
Classifier: Programming Language :: Python :: 3.8
Classifier: Programming Language :: Python :: 3.9
Classifier: Programming Language :: Python :: 3.10
Classifier: Programming Language :: Python :: 3.11
Requires-Python: >=3.8
Requires-Dist: requests>=2.31.0
Requires-Dist: joblib>=1.3.0
Requires-Dist: pandas>=2.0.0
Requires-Dist: scikit-learn>=1.0.0
Requires-Dist: tqdm>=4.65.0
Dynamic: author
Dynamic: author-email
Dynamic: classifier
Dynamic: description
Dynamic: description-content-type
Dynamic: home-page
Dynamic: requires-dist
Dynamic: requires-python
Dynamic: summary
